lptp/client/__init__.py
lptp/client/client.py
lptp/exceptions/__init__.py
lptp/exceptions/base.py
lptp/exceptions/client.py
lptp/exceptions/data.py
lptp/server/__init__.py
lptp/server/file_generator.py
lptp/server/log.py
lptp/server/manager.py
lptp/server/procedure.py
lptp/server/server.py
lptp/types/__init__.py
lptp/types/packets/__init__.py
lptp/types/packets/auth.py
lptp/types/packets/base.py
lptp/types/packets/exit.py
lptp/types/packets/procedure.py
lptp/types/packets/status.py
lptp/types/pds/__init__.py
lptp/types/pds/field.py
lptp/types/pds/pds.py
lptp/types/pds/types/__init__.py
lptp/types/pds/types/base.py
lptp/types/pds/types/bool.py
lptp/types/pds/types/int.py
lptp/types/pds/types/list.py
lptp/types/pds/types/other.py
lptp/types/pds/types/str.py
lptp-1.0.2.dist-info/LICENSE
lptp-1.0.2.dist-info/METADATA
lptp-1.0.2.dist-info/WHEEL
lptp-1.0.2.dist-info/top_level.txt
lptp-1.0.2.dist-info/RECORD
