Metadata-Version: 2.1
Name: lptp
Version: 1.0.2
Summary: Данный протокол является протоколом RPC вида и служит для вызова процедур на удалённом сервере. Проект является исключительно учебным и не рекомендуется для реального использования.
Home-page: https://github.com/Zoom-Developer/LPTP
Author: zoomdev
Author-email: zoomdeveloper@yandex.ru
Keywords: rpc
Requires-Python: >=3.10
License-File: LICENSE
